<?xml version="1.0" encoding="utf-8" ?><dwsync><file name=".gitattributes" server="Macintosh HD/Applications/MAMP/htdocs/DW/bookrank/" local="3516529502" remote="3516529502" Dst="-1" /><file name=".gitignore" server="Macintosh HD/Applications/MAMP/htdocs/DW/bookrank/" local="3516529502" remote="3516529502" Dst="-1" /><file name="autoload.php" server="Macintosh HD/Applications/MAMP/htdocs/DW/bookrank/" local="3516529502" remote="3516529502" Dst="-1" /><file name="CHANGELOG.md" server="Macintosh HD/Applications/MAMP/htdocs/DW/bookrank/" local="3516529502" remote="3516529502" Dst="-1" /><file name="composer.json" server="Macintosh HD/Applications/MAMP/htdocs/DW/bookrank/" local="3516529502" remote="3516529502" Dst="-1" /><file name="LICENSE" server="Macintosh HD/Applications/MAMP/htdocs/DW/bookrank/" local="3516529502" remote="3516529502" Dst="-1" /><file name="README.en.md" server="Macintosh HD/Applications/MAMP/htdocs/DW/bookrank/" local="3516529502" remote="3516529502" Dst="-1" /><file name="README.md" server="Macintosh HD/Applications/MAMP/htdocs/DW/bookrank/" local="3516529502" remote="3516529502" Dst="-1" /><file name=".gitattributes" server="ftp.edasan.daa.jp//bookrank/" local="3516529502" remote="3642987900" Dst="-1" /><file name=".gitignore" server="ftp.edasan.daa.jp//bookrank/" local="3516529502" remote="3642987900" Dst="-1" /><file name="autoload.php" server="ftp.edasan.daa.jp//bookrank/" local="3516529502" remote="3642987900" Dst="-1" /><file name="CHANGELOG.md" server="ftp.edasan.daa.jp//bookrank/" local="3516529502" remote="3642987900" Dst="-1" /><file name="composer.json" server="ftp.edasan.daa.jp//bookrank/" local="3516529502" remote="3642987900" Dst="-1" /><file name="LICENSE" server="ftp.edasan.daa.jp//bookrank/" local="3516529502" remote="3642987900" Dst="-1" /><file name="README.en.md" server="ftp.edasan.daa.jp//bookrank/" local="3516529502" remote="3642987900" Dst="-1" /><file name="README.md" server="ftp.edasan.daa.jp//bookrank/" local="3516529502" remote="3642987900" Dst="-1" /><file name="config.php" server="Macintosh HD/Applications/MAMP/htdocs/DW/bookrank/" local="3643082700" remote="3643082700" Dst="-1" /><file name="config.php" server="ftp.edasan.daa.jp//bookrank/" local="3643082700" remote="3643082700" Dst="-1" /></dwsync>